XGame/__init__.py
XGame/setup.py
XGame/docs/__init__.py
XGame_Py-0.0.3.dist-info/METADATA
XGame_Py-0.0.3.dist-info/WHEEL
XGame_Py-0.0.3.dist-info/top_level.txt
XGame_Py-0.0.3.dist-info/RECORD
