Metadata-Version: 2.1
Name: XGame-Py
Version: 0.0.3
Summary: The Most Strongest Game Engine in python
Home-page: https://google.com
Author: FeedFall8
Author-email: FeedFall8@gmail.com
License: UNKNOWN
Platform: UNKNOWN
Classifier: Programming Language :: Python :: 3
Classifier: License :: OSI Approved :: MIT License
Classifier: Operating System :: OS Independent
Requires-Python: >=3.0
